volbf/__init__.py
volbf/addrspace.py
volbf/cache.py
volbf/commands.py
volbf/conf.py
volbf/constants.py
volbf/debug.py
volbf/dwarf.py
volbf/exceptions.py
volbf/fmtspec.py
volbf/obj.py
volbf/poolscan.py
volbf/protos.py
volbf/py.py
volbf/registry.py
volbf/scan.py
volbf/timefmt.py
volbf/utils.py
volbf/validity.py
volbf/plugins/__init__.py
volbf/plugins/bigpagepools.py
volbf/plugins/bioskbd.py
volbf/plugins/cmdline.py
volbf/plugins/common.py
volbf/plugins/connections.py
volbf/plugins/connscan.py
volbf/plugins/crashinfo.py
volbf/plugins/dlldump.py
volbf/plugins/drivermodule.py
volbf/plugins/dumpcerts.py
volbf/plugins/dumpfiles.py
volbf/plugins/envars.py
volbf/plugins/evtlogs.py
volbf/plugins/fileparam.py
volbf/plugins/filescan.py
volbf/plugins/getservicesids.py
volbf/plugins/getsids.py
volbf/plugins/handles.py
volbf/plugins/heaps.py
volbf/plugins/hibinfo.py
volbf/plugins/hpakinfo.py
volbf/plugins/iehistory.py
volbf/plugins/imagecopy.py
volbf/plugins/imageinfo.py
volbf/plugins/joblinks.py
volbf/plugins/kdbgscan.py
volbf/plugins/kpcrscan.py
volbf/plugins/machoinfo.py
volbf/plugins/mbrparser.py
volbf/plugins/mftparser.py
volbf/plugins/moddump.py
volbf/plugins/modscan.py
volbf/plugins/modules.py
volbf/plugins/multiscan.py
volbf/plugins/netscan.py
volbf/plugins/notepad.py
volbf/plugins/objtypescan.py
volbf/plugins/patcher.py
volbf/plugins/patchguard.py
volbf/plugins/pooltracker.py
volbf/plugins/privileges.py
volbf/plugins/procdump.py
volbf/plugins/pstree.py
volbf/plugins/raw2dmp.py
volbf/plugins/sockets.py
volbf/plugins/sockscan.py
volbf/plugins/ssdt.py
volbf/plugins/strings.py
volbf/plugins/taskmods.py
volbf/plugins/tcaudit.py
volbf/plugins/timeliner.py
volbf/plugins/vadinfo.py
volbf/plugins/vboxinfo.py
volbf/plugins/verinfo.py
volbf/plugins/vmwareinfo.py
volbf/plugins/volshell.py
volbf/plugins/win10cookie.py
volbf/plugins/addrspaces/__init__.py
volbf/plugins/addrspaces/amd64.py
volbf-2.6.7.dist-info/DESCRIPTION.rst
volbf-2.6.7.dist-info/METADATA
volbf-2.6.7.dist-info/RECORD
volbf-2.6.7.dist-info/WHEEL
volbf-2.6.7.dist-info/metadata.json
volbf-2.6.7.dist-info/top_level.txt
