Metadata-Version: 2.0
Name: volbf
Version: 2.6.7
Summary: volbf -- Volatile memory framework
Home-page: http://www.volbffoundation.org
Author: AAron Walters
Author-email: awalters@4tphi.net
License: GPL
Platform: UNKNOWN
